README.rst
setup.py
antispoofing/__init__.py
antispoofing.competition_icb2013.egg-info/PKG-INFO
antispoofing.competition_icb2013.egg-info/SOURCES.txt
antispoofing.competition_icb2013.egg-info/dependency_links.txt
antispoofing.competition_icb2013.egg-info/entry_points.txt
antispoofing.competition_icb2013.egg-info/namespace_packages.txt
antispoofing.competition_icb2013.egg-info/requires.txt
antispoofing.competition_icb2013.egg-info/top_level.txt
antispoofing.competition_icb2013.egg-info/zip-safe
antispoofing/competition_icb2013/__init__.py
antispoofing/competition_icb2013/helpers/__init__.py
antispoofing/competition_icb2013/helpers/database.py
antispoofing/competition_icb2013/helpers/helpers.py
antispoofing/competition_icb2013/script/__init__.py
antispoofing/competition_icb2013/script/calcglcm.py
antispoofing/competition_icb2013/script/crop_faces.py
antispoofing/competition_icb2013/script/icb2013_facebb_countermeasure.py
antispoofing/competition_icb2013/script/icb2013_qstatistic.py
antispoofing/competition_icb2013/script/ldatrain.py
antispoofing/competition_icb2013/script/svmtrain.py