Metadata-Version: 1.0
Name: antispoofing.competition-icb2013
Version: 1.0.0
Summary: Fusion of spoofing counter measures for the REPLAY-ATTACK database (competition entry for 2nd competition on counter measures to 2D facial spoofing attacks, ICB 2013)
Home-page: http://pypi.python.org/pypi/antispoofing.competition_icb2013
Author: Ivana Chingovska
Author-email: ivana.chingovska@idiap.ch
License: GPLv3
Platform: UNKNOWN
